{
  "name": "demo-world",
  "title": "The Forge Demo and Tutorial",
  "description": "<h2>To login, use the access key:  <strong>forge</strong></h2>\n<p>Discover all the great features of Foundry VTT!</p>\n<p>This demo serves as a Tutorial of Foundry VTT’s features.</p>\n<p>This is still a work in progress.</p>\n<h2>To login, use the access key:  <strong>forge</strong></h2>",
  "authors": [
    "Kevin",
    "ForgeVTT"
  ],
  "url": "https://github.com/KevinTheKittyCat/demo-world-ForgeVtt",
  "flags": {},
  "version": "1.1.0",
  "minimumCoreVersion": "0.8.8",
  "compatibleCoreVersion": "1.0.0",
  "scripts": [
    "Demo-Ready-Hooks.js"
  ],
  "esmodules": [],
  "styles": [],
  "languages": [],
  "packs": [
    {
      "label": "Nice",
      "entity": "Item",
      "name": "nice",
      "path": "packs/nice.db",
      "system": "dnd5e",
      "package": "world",
      "absPath": "/forge-vtt/users/5e4d44f141c29601b2167a91/Games/demo2/Data/worlds/demo2/packs/nice.db",
      "private": false
    },
    {
      "label": "Store",
      "entity": "Item",
      "name": "store",
      "path": "packs/store.db",
      "system": "dnd5e",
      "package": "world",
      "absPath": "/forge-vtt/users/5e4d44f141c29601b2167a91/Games/demo2/Data/worlds/demo2/packs/store.db",
      "private": false
    },
    {
      "label": "Goods",
      "entity": "Item",
      "name": "goods",
      "path": "packs/goods.db",
      "system": "dnd5e",
      "package": "world",
      "absPath": "/forge-vtt/users/5e4d44f141c29601b2167a91/Games/demo2/Data/worlds/demo2/packs/goods.db",
      "private": false
    }
  ],
  "system": "dnd5e",
  "dependencies": [
    {
      "type": "module",
      "name": "trigger-happy"
    },
    {
      "type": "module",
      "name": "advanced-macros"
    },
    {
      "type": "module",
      "name": "scene-transitions"
    },
    {
      "type": "module",
      "name": "parallaxia"
    },
    {
      "type": "module",
      "name": "itemacro"
    },
    {
      "type": "module",
      "name": "lib-wrapper"
    },
    {
      "type": "system",
      "name": "dnd5e"
    }
  ],
  "socket": false,
  "manifest": "https://github.com/KevinTheKittyCat/demo-world-ForgeVtt/releases/latest/download/world.json",
  "download": "https://github.com/KevinTheKittyCat/demo-world-ForgeVtt/releases/download/1.1.0/world.zip",
  "protected": false,
  "coreVersion": "0.8.9",
  "resetKeys": false,
  "safeMode": false,
  "systemVersion": "1.4.3"
}